sensorsio/__init__.py
sensorsio/ecostress.py
sensorsio/ecostress_v2.py
sensorsio/hls.py
sensorsio/irregulargrid.py
sensorsio/landsat.py
sensorsio/master.py
sensorsio/mgrs.py
sensorsio/py.typed
sensorsio/regulargrid.py
sensorsio/sentinel2.py
sensorsio/sentinel2_l1c.py
sensorsio/srtm.py
sensorsio/storage.py
sensorsio/utils.py
sensorsio/venus.py
sensorsio/worldclim.py
sensorsio/data/sentinel2/mgrs_tiles.gpkg
sensorsio/data/sentinel2/mgrs_tiles.gpkg.zip
sensorsio/data/sentinel2/orbits.gpkg
sensorsio/data/sentinel2/srs_sentinel2a.csv
sensorsio/data/sentinel2/srs_sentinel2b.csv
sensorsio/data/sentinel2/theia_s2.gpkg
sensorsio/data/venus/srs_venus.csv
sensorsio/data/venus/srs_venus.txt
sensorsio/data/venus/theia_venus.gpkg
sensorsio-1.0.2.dist-info/METADATA
sensorsio-1.0.2.dist-info/WHEEL
sensorsio-1.0.2.dist-info/licenses/AUTHORS.rst
sensorsio-1.0.2.dist-info/licenses/LICENSE-Apache-2.0
sensorsio-1.0.2.dist-info/licenses/LICENSE-LGPL-3.0
sensorsio-1.0.2.dist-info/licenses/NOTICE
sensorsio-1.0.2.dist-info/RECORD
