Metadata-Version: 2.3
Name: sensorsio
Version: 1.0.2
Summary: Conventient functions to load remote sensing data to numpy and xarray
Project-URL: Homepage, https://framagit.org/jmichel-otb/sensorsio
Author-email: Julien Michel <julien.michel@cnes.fr>
License-Expression: Apache-2.0 OR LGPL-3.0
License-File: AUTHORS.rst
License-File: LICENSE-Apache-2.0
License-File: LICENSE-LGPL-3.0
License-File: NOTICE
Classifier: Development Status :: 4 - Beta
Classifier: Programming Language :: Python
Requires-Python: >=3.10
Requires-Dist: affine>=2.4.0
Requires-Dist: boto3>=1.34.149
Requires-Dist: fiona<2,>=1.9.6
Requires-Dist: geopandas>=1.0.1
Requires-Dist: h5py>=3.11.0
Requires-Dist: hatch>=1.12.0
Requires-Dist: importlib-metadata>=8.2.0
Requires-Dist: mgrs>=1.5.0
Requires-Dist: numpy>=2
Requires-Dist: pandas-stubs>=2.2.2.240603
Requires-Dist: pandas>=2.2.2
Requires-Dist: pybind11>=2.12
Requires-Dist: pyhdf>=0.11.4
Requires-Dist: pyproj>=3.6.1
Requires-Dist: pyresample>=1.28.4
Requires-Dist: rasterio>=1.3.10
Requires-Dist: scikit-learn>=1.5.1
Requires-Dist: scipy>=1.14.0
Requires-Dist: utm>=0.7.0
Requires-Dist: xarray>=2024.6.0
Provides-Extra: dev
Requires-Dist: hatch>=1.12.0; extra == 'dev'
Requires-Dist: hatchling>=1.25.0; extra == 'dev'
Requires-Dist: mypy>=1.11.2; extra == 'dev'
Requires-Dist: pre-commit>=3.8.0; extra == 'dev'
Requires-Dist: pylint>=3.2.7; extra == 'dev'
Provides-Extra: doc
Requires-Dist: nbsphinx-link>=1.3.1; extra == 'doc'
Requires-Dist: nbsphinx>=0.9.5; extra == 'doc'
Requires-Dist: sphinx-mdinclude>=0.6.2; extra == 'doc'
Requires-Dist: sphinx-rtd-theme>=2.0.0; extra == 'doc'
Requires-Dist: sphinx>=7.4.7; extra == 'doc'
Provides-Extra: notebook
Requires-Dist: ipykernel>=6.29.5; extra == 'notebook'
Requires-Dist: matplotlib>=3.9.1; extra == 'notebook'
Requires-Dist: notebook>=7.2.1; extra == 'notebook'
Provides-Extra: testing
Requires-Dist: pytest-cov>=5.0.0; extra == 'testing'
Requires-Dist: pytest>=8.3.2; extra == 'testing'
